dnsq.py
dnsq-1.1.4.dist-info/zip-safe
dnsq-1.1.4.dist-info/RECORD
dnsq-1.1.4.dist-info/top_level.txt
dnsq-1.1.4.dist-info/DESCRIPTION.rst
dnsq-1.1.4.dist-info/METADATA
dnsq-1.1.4.dist-info/metadata.json
dnsq-1.1.4.dist-info/WHEEL
