Metadata-Version: 2.0
Name: dnsq
Version: 1.1.4
Summary: DNS Query Tool
Home-page: http://www.mailgun.com
Author: Rackspace
Author-email: admin@mailgunhq.com
License: Apache 2
Platform: UNKNOWN
Requires-Dist: dnspython (>=1.11.1)
Requires-Dist: expiringdict (>=1.1)
